currensees/__init__.py
currensees/auth.py
currensees/convert.py
currensees/convert_all.py
currensees/currencies.py
currensees/daily_average.py
currensees/historical.py
currensees/margins_spreads.py
currensees/monthly_average.py
currensees/performances.py
currensees/signals.py
currensees/version.py
currensees/weekly_average.py
currensees-1.1.1.dist-info/LICENSE
currensees-1.1.1.dist-info/METADATA
currensees-1.1.1.dist-info/WHEEL
currensees-1.1.1.dist-info/top_level.txt
currensees-1.1.1.dist-info/RECORD
